astroz/__init__.py
astroz/_astroz.cpython-312-x86_64-linux-gnu.so
astroz/_astroz.pyi
astroz/_astroz.so
astroz/py.typed
astroz-0.6.1.dist-info/METADATA
astroz-0.6.1.dist-info/WHEEL
astroz-0.6.1.dist-info/top_level.txt
astroz-0.6.1.dist-info/RECORD
