Metadata-Version: 2.4
Name: astroz
Version: 0.6.1
Summary: Python bindings for astroz - high-performance astrodynamics library
License: MIT
Project-URL: Repository, https://github.com/ATTron/astroz
Keywords: astrodynamics,orbital-mechanics,sgp4,tle,satellite
Classifier: Development Status :: 3 - Alpha
Classifier: Intended Audience :: Science/Research
Classifier: License :: OSI Approved :: MIT License
Classifier: Programming Language :: Python :: 3
Classifier: Topic :: Scientific/Engineering :: Astronomy
Requires-Python: >=3.10
Requires-Dist: numpy
Provides-Extra: dev
Requires-Dist: sgp4; extra == "dev"
Provides-Extra: docs
Requires-Dist: pdoc; extra == "docs"
